pyqcolur/__init__.py
pyqcolur/test.py
pyqcolur-1.1.dist-info/METADATA
pyqcolur-1.1.dist-info/WHEEL
pyqcolur-1.1.dist-info/top_level.txt
pyqcolur-1.1.dist-info/RECORD
