Metadata-Version: 2.1
Name: pyqcolur
Version: 1.1
Summary: python library for colors
Author-email: yksick@gmail.com
License: Eclipse Public License 2.0
